foliant/preprocessors/imagineui.py
foliantcontrib.imagineui-1.0.0.dist-info/LICENSE
foliantcontrib.imagineui-1.0.0.dist-info/METADATA
foliantcontrib.imagineui-1.0.0.dist-info/WHEEL
foliantcontrib.imagineui-1.0.0.dist-info/top_level.txt
foliantcontrib.imagineui-1.0.0.dist-info/RECORD
